oci_cli/__init__.py
oci_cli/cli.py
oci_cli/cli_clients.py
oci_cli/cli_constants.py
oci_cli/cli_exceptions.py
oci_cli/cli_root.py
oci_cli/cli_setup.py
oci_cli/cli_util.py
oci_cli/final_command_processor.py
oci_cli/formatting.py
oci_cli/json_skeleton_utils.py
oci_cli/oci_template.py
oci_cli/retry_utils.py
oci_cli/string_utils.py
oci_cli/version.py
oci_cli/aliasing/__init__.py
oci_cli/aliasing/command_group_with_alias.py
oci_cli/aliasing/parameter_alias.py
oci_cli/bin/OciTabExpansion.ps1
oci_cli/bin/announce.psm1
oci_cli/bin/announcements-service.psm1
oci_cli/bin/audit.psm1
oci_cli/bin/bv.psm1
oci_cli/bin/ce.psm1
oci_cli/bin/compute-management.psm1
oci_cli/bin/compute.psm1
oci_cli/bin/db.psm1
oci_cli/bin/dns.psm1
oci_cli/bin/email.psm1
oci_cli/bin/fs.psm1
oci_cli/bin/iam.psm1
oci_cli/bin/kms.psm1
oci_cli/bin/lb.psm1
oci_cli/bin/monitoring.psm1
oci_cli/bin/network.psm1
oci_cli/bin/oci_autocomplete.sh
oci_cli/bin/os.psm1
oci_cli/bin/search.psm1
oci_cli/bin/setup.psm1
oci_cli/custom_types/__init__.py
oci_cli/custom_types/cli_case_insensitive_choice.py
oci_cli/custom_types/cli_complex_type.py
oci_cli/custom_types/cli_datetime.py
oci_cli/custom_types/cli_from_json.py
oci_cli/custom_types/object_storage_bulk_operation_output.py
oci_cli/extended/__init__.py
oci_cli/file_filters/__init__.py
oci_cli/file_filters/file_filter_collection.py
oci_cli/file_filters/file_path_filter.py
oci_cli/generated/__init__.py
oci_cli/generated/announcement_cli.py
oci_cli/generated/audit_cli.py
oci_cli/generated/blockstorage_cli.py
oci_cli/generated/compute_cli.py
oci_cli/generated/computemanagement_cli.py
oci_cli/generated/containerengine_cli.py
oci_cli/generated/core_service_cli.py
oci_cli/generated/database_cli.py
oci_cli/generated/dns_cli.py
oci_cli/generated/email_cli.py
oci_cli/generated/filestorage_cli.py
oci_cli/generated/identity_cli.py
oci_cli/generated/kms_service_cli.py
oci_cli/generated/kmscrypto_cli.py
oci_cli/generated/kmsmanagement_cli.py
oci_cli/generated/kmsvault_cli.py
oci_cli-2.4.43.dist-info/LICENSE.txt
oci_cli-2.4.43.dist-info/METADATA
oci_cli-2.4.43.dist-info/WHEEL
oci_cli-2.4.43.dist-info/entry_points.txt
oci_cli-2.4.43.dist-info/top_level.txt
oci_cli-2.4.43.dist-info/RECORD
