Metadata-Version: 2.1
Name: oci-cli
Version: 2.4.43
Summary: Oracle Cloud Infrastructure CLI
Home-page: https://docs.us-phoenix-1.oraclecloud.com/Content/API/SDKDocs/cli.htm
Author: Oracle
Author-email: joe.levy@oracle.com
License: Universal Permissive License 1.0 or Apache License 2.0
Platform: UNKNOWN
Classifier: Development Status :: 5 - Production/Stable
Classifier: Environment :: Console
Classifier: Intended Audience :: Information Technology
Classifier: Intended Audience :: Developers
Classifier: License :: OSI Approved :: Apache Software License
Classifier: License :: OSI Approved :: Universal Permissive License (UPL)
Classifier: Programming Language :: Python :: 2.7
Classifier: Programming Language :: Python :: 3.5
Classifier: Programming Language :: Python :: 3.6
Requires-Dist: oci (==2.1.6)
Requires-Dist: arrow (==0.10.0)
Requires-Dist: certifi
Requires-Dist: click (==6.7)
Requires-Dist: configparser (==3.5.0)
Requires-Dist: cryptography (==2.4.2)
Requires-Dist: cx-Oracle (==7.0)
Requires-Dist: httpsig-cffi (==15.0.0)
Requires-Dist: jmespath (==0.9.3)
Requires-Dist: python-dateutil (==2.7.3)
Requires-Dist: pytz (==2016.10)
Requires-Dist: retrying (==1.3.3)
Requires-Dist: six (==1.11.0)
Requires-Dist: terminaltables (==3.1.0)
Requires-Dist: idna (<2.7,>=2.5)
Requires-Dist: pyOpenSSL (==18.0.0)
